Workbook

Sheet LAUREANO 
A1: FECHA | B1: Cant. | C1: Total Facturado | D1: VALHALLA | E1: LAUREANO | F1: TRANSF.
A2: SEMANA 1 | H2: Total | I2: =C8+C16+C24+C32+C40 -> 2704000
D3: =+C3/2 -> 0 | E3: =+D3 -> 0 | H3: Total VALHALLA | I3: =D8+D16+D24+D32+D40 -> 1352000
A4: 46113 | B4: 8 | C4: 129000 | D4: =+C4/2 -> 64500 | E4: =+D4 -> 64500 | F4: 129000 | H4: Total LAUREANO | I4: =E8+E24+E32+E40+E16 -> 1352000
A5: 46114 | B5: 7 | C5: 124000 | D5: =+C5/2 -> 62000 | E5: =+D5 -> 62000 | F5: 74000
A6: 46115 | B6: 4 | C6: 70000 | D6: =+C6/2 -> 35000 | E6: =+D6 -> 35000 | F6: 34000 | H6: Total CORTES | I6: =+B8+B16+B24+B32+B40 -> 157
A7: 46116 | B7: 5 | C7: 93000 | D7: =+C7/2 -> 46500 | E7: =+D7 -> 46500 | F7: 58000
A8: Total | B8: =SUM(B3:B7) -> 24 | C8: =SUM(C3:C7) -> 416000 | D8: =SUM(D3:D7) -> 208000 | E8: =SUM(E3:E7) -> 208000 | F8: =SUM(F3:F7) -> 295000
A10: SEMANA 2
A11: 46119 | B11: 4 | C11: 69000 | D11: =+C11/2 -> 34500 | E11: =+D11 -> 34500 | F11: 18000
A12: 46120 | B12: 4 | C12: 60000 | D12: =+C12/2 -> 30000 | E12: =+D12 -> 30000 | F12: 33000
A13: 46121 | B13: 11 | C13: 185000 | D13: =+C13/2 -> 92500 | E13: =+D13 -> 92500 | F13: 104000
A14: 46122 | B14: 12 | C14: 214000 | D14: =+C14/2 -> 107000 | E14: =+D14 -> 107000 | F14: 123000
A15: 46123 | B15: 6 | C15: 107000 | D15: =+C15/2 -> 53500 | E15: =+D15 -> 53500 | F15: 95000
A16: Total | B16: =SUM(B11:B15) -> 37 | C16: =SUM(C11:C15) -> 635000 | D16: =SUM(D11:D15) -> 317500 | E16: =SUM(E11:E15) -> 317500 | F16: =SUM(F11:F15) -> 373000
A18: SEMANA 3
A19: 46126 | B19: 8 | C19: 135000 | D19: =+C19/2 -> 67500 | E19: =+D19 -> 67500 | F19: 69000
A20: 46127 | B20: 1 | C20: 18000 | D20: =+C20/2 -> 9000 | E20: =+D20 -> 9000 | F20: 18000
A21: 46128 | B21: 8 | C21: 136000 | D21: =+C21/2 -> 68000 | E21: =+D21 -> 68000 | F21: 85000
A22: 46129 | B22: 12 | C22: 199000 | D22: =+C22/2 -> 99500 | E22: =+D22 -> 99500 | F22: 136000
A23: 46130 | B23: 7 | C23: 125000 | D23: =+C23/2 -> 62500 | E23: =+D23 -> 62500 | F23: 76000
A24: Total | B24: =SUM(B19:B23) -> 36 | C24: =SUM(C19:C23) -> 613000 | D24: =SUM(D19:D23) -> 306500 | E24: =SUM(E19:E23) -> 306500 | F24: =SUM(F19:F23) -> 384000
A26: SEMANA 4
A27: 46133 | B27: 3 | C27: 55000 | D27: =+C27/2 -> 27500 | E27: =+D27 -> 27500 | F27: 55000
A28: 46134 | B28: 6 | C28: 106000 | D28: =+C28/2 -> 53000 | E28: =+D28 -> 53000 | F28: 71000
A29: 46135 | B29: 11 | C29: 185000 | D29: =+C29/2 -> 92500 | E29: =+D29 -> 92500 | F29: 149000
A30: 46136 | B30: 11 | C30: 197000 | D30: =+C30/2 -> 98500 | E30: =+D30 -> 98500 | F30: 125000
A31: 46137 | B31: 7 | C31: 118000 | D31: =+C31/2 -> 59000 | E31: =+D31 -> 59000 | F31: 63000
A32: Total | B32: =SUM(B27:B31) -> 38 | C32: =SUM(C27:C31) -> 661000 | D32: =SUM(D27:D31) -> 330500 | E32: =SUM(E27:E31) -> 330500 | F32: =SUM(F27:F31) -> 463000
A34: SEMANA 5
A35: 46140 | B35: 5 | C35: 86000 | D35: =+C35/2 -> 43000 | E35: =+D35 -> 43000 | F35: 68000
A36: 46141 | B36: 6 | C36: 105000 | D36: =+C36/2 -> 52500 | E36: =+D36 -> 52500 | F36: 105000
A37: 46142 | B37: 11 | C37: 188000 | D37: =+C37/2 -> 94000 | E37: =+D37 -> 94000 | F37: 143000
D38: =+C38/2 -> 0 | E38: =+D38 -> 0
D39: =+C39/2 -> 0 | E39: =+D39 -> 0
A40: Total | B40: =SUM(B35:B39) -> 22 | C40: =SUM(C35:C39) -> 379000 | D40: =SUM(D35:D39) -> 189500 | E40: =SUM(E35:E39) -> 189500 | F40: =SUM(F35:F39) -> 316000

Sheet FRANCO
A1: FECHA | B1: Cant. | C1: Total Facturado | D1: VALHALLA | E1: LAUTARO
A2: SEMANA 1 | G2: Total | H2: =C8+C16+C24+C32+C40 -> 2538000
D3: =+C3/2 -> 0 | E3: =+D3 -> 0 | G3: Total VALHALLA | H3: 1275000
A4: 46113 | B4: 8 | C4: 143000 | D4: =+C4/2 -> 71500 | E4: =+D4 -> 71500 | G4: Total FRANCO | H4: =+H2-H3 -> 1263000
A5: 46114 | B5: 5 | C5: 77000 | D5: =+C5/2 -> 38500 | E5: =+D5 -> 38500
A6: 46115 | B6: 3 | C6: 65000 | D6: =+C6/2 -> 32500 | E6: =+D6 -> 32500 | G6: Total CORTES | H6: =+B8+B16+B24+B32+B40 -> 148
A7: 46116 | B7: 4 | C7: 73000 | D7: =+C7/2 -> 36500 | E7: =+D7 -> 36500
A8: Total | B8: =SUM(B2:B7) -> 20 | C8: =SUM(C2:C7) -> 358000 | D8: =SUM(D2:D7) -> 179000 | E8: =SUM(E2:E7) -> 179000
A10: SEMANA 2
A11: 46119 | B11: 5 | C11: 88000 | D11: =+C11/2 -> 44000 | E11: =+D11 -> 44000
A12: 46120 | B12: 5 | C12: 86000 | D12: =+C12/2 -> 43000 | E12: =+D12 -> 43000
A13: 46121 | B13: 8 | C13: 136000 | D13: =+C13/2 -> 68000 | E13: =+D13 -> 68000
A14: 46122 | B14: 11 | C14: 187000 | D14: =+C14/2 -> 93500 | E14: =+D14 -> 93500
A15: 46123 | B15: 7 | C15: 127000 | D15: =+C15/2 -> 63500 | E15: =+D15 -> 63500
A16: Total | B16: =SUM(B10:B15) -> 36 | C16: =SUM(C11:C15) -> 624000 | D16: =SUM(D11:D15) -> 312000 | E16: =SUM(E11:E15) -> 312000
A18: SEMANA 3
A19: 46126 | B19: 9 | C19: 144000 | D19: =+C19/2 -> 72000 | E19: =+D19 -> 72000
A20: 46127 | B20: 4 | C20: 70000 | D20: =+C20/2 -> 35000 | E20: =+D20 -> 35000
A21: 46128 | B21: 6 | C21: 107000 | D21: =+C21/2 -> 53500 | E21: =+D21 -> 53500
A22: 46129 | B22: 9 | C22: 163000 | D22: =+C22/2 -> 81500 | E22: =+D22 -> 81500
A23: 46130 | B23: 13 | C23: 208000 | D23: =+C23/2 -> 104000 | E23: =+D23 -> 104000
A24: Total | B24: =SUM(B18:B23) -> 41 | C24: =SUM(C19:C23) -> 692000 | D24: =SUM(D19:D23) -> 346000 | E24: =SUM(E19:E23) -> 346000
A26: SEMANA 4
A27: 46133 | B27: 7 | C27: 117000 | D27: =+C27/2 -> 58500 | E27: =+D27 -> 58500
A28: 46134 | B28: 7 | C28: 123000 | D28: =+C28/2 -> 61500 | E28: =+D28 -> 61500
A29: 46135 | B29: 8 | C29: 130000 | D29: =+C29/2 -> 65000 | E29: =+D29 -> 65000
A30: 46136 | B30: 6 | C30: 99000 | D30: =+C30/2 -> 49500 | E30: =+D30 -> 49500
A31: 46137 | B31: 4 | C31: 76000 | D31: =+C31/2 -> 38000 | E31: =+D31 -> 38000
A32: Total | B32: =SUM(B26:B31) -> 32 | C32: =SUM(C27:C31) -> 545000 | D32: =SUM(D27:D31) -> 272500 | E32: =SUM(E27:E31) -> 272500
A34: SEMANA 5
A35: 46140 | B35: 7 | C35: 121000 | D35: =+C35/2 -> 60500 | E35: =+D35 -> 60500
A36: 46141 | B36: 4 | C36: 66000 | D36: =+C36/2 -> 33000 | E36: =+D36 -> 33000
A37: 46142 | B37: 8 | C37: 132000 | D37: =+C37/2 -> 66000 | E37: =+D37 -> 66000
D38: =+C38/2 -> 0 | E38: =+D38 -> 0
D39: =+C39/2 -> 0 | E39: =+D39 -> 0
A40: Total | B40: =SUM(B34:B39) -> 19 | C40: =SUM(C35:C39) -> 319000 | D40: =SUM(D35:D39) -> 159500 | E40: =SUM(E35:E39) -> 159500

Sheet BEIZEN
A1: FECHA | B1: Cant. | C1: Total Facturado | D1: VALHALLA | E1: BEIZEN | F1: TRANSF.
A2: SEMANA 1 | H2: Total | I2: =C8+C16+C24+C32+C40 -> 1526000
D3: =+C3/2 -> 0 | E3: =+D3 -> 0 | H3: Total VALHALLA | I3: =D8+D16+D24+D32+D40 -> 763000
A4: 46113 | B4: 7 | C4: 114000 | D4: =+C4/2 -> 57000 | E4: =+D4 -> 57000 | F4: 99000 | H4: Total BEIZEN | I4: =E8+E16+E24+E32+E40 -> 763000
A5: 46114 | D5: =+C5/2 -> 0 | E5: =+D5 -> 0
A6: 46115 | D6: =+C6/2 -> 0 | E6: =+D6 -> 0 | H6: Total CORTES | I6: =+B8+B16+B24+B32+B40 -> 105
A7: 46116 | B7: 7 | C7: 104000 | D7: =+C7/2 -> 52000 | E7: =+D7 -> 52000 | F7: 86000
A8: Total | B8: =SUM(B3:B7) -> 14 | C8: =SUM(C2:C7) -> 218000 | D8: =SUM(D2:D7) -> 109000 | E8: =SUM(E2:E7) -> 109000 | F8: =SUM(F3:F7) -> 185000
A10: SEMANA 2
A11: 46119 | B11: 6 | C11: 108000 | D11: =+C11/2 -> 54000 | E11: =+D11 -> 54000
A12: 46120 | B12: 6 | C12: 81000 | D12: =+C12/2 -> 40500 | E12: =+D12 -> 40500
A13: 46121 | B13: 7 | C13: 98000 | D13: =+C13/2 -> 49000 | E13: =+D13 -> 49000
A14: 46122 | B14: 5 | C14: 83000 | D14: =+C14/2 -> 41500 | E14: =+D14 -> 41500
A15: 46123 | B15: 6 | C15: 98000 | D15: =+C15/2 -> 49000 | E15: =+D15 -> 49000
A16: Total | B16: =SUM(B11:B15) -> 30 | C16: =SUM(C11:C15) -> 468000 | D16: =SUM(D11:D15) -> 234000 | E16: =SUM(E11:E15) -> 234000 | F16: =SUM(F11:F15) -> 0
A18: SEMANA 3
A19: 46126 | B19: 6 | C19: 88000 | D19: =+C19/2 -> 44000 | E19: =+D19 -> 44000 | F19: 70000
A20: 46127 | B20: 3 | C20: 33000 | D20: =+C20/2 -> 16500 | E20: =+D20 -> 16500 | F20: 33000
A21: 46128 | B21: 4 | C21: 66000 | D21: =+C21/2 -> 33000 | E21: =+D21 -> 33000 | F21: 30000
A22: 46129 | B22: 7 | C22: 99000 | D22: =+C22/2 -> 49500 | E22: =+D22 -> 49500 | F22: 66000
A23: 46130 | B23: 2 | C23: 15000 | D23: =+C23/2 -> 7500 | E23: =+D23 -> 7500
A24: Total | B24: =SUM(B19:B23) -> 22 | C24: =SUM(C19:C23) -> 301000 | D24: =SUM(D19:D23) -> 150500 | E24: =SUM(E19:E23) -> 150500 | F24: =SUM(F19:F23) -> 199000
A26: SEMANA 4
A27: 46133 | B27: 4 | C27: 33000 | D27: =+C27/2 -> 16500 | E27: =+D27 -> 16500 | F27: 33000
A28: 46134 | B28: 5 | C28: 81000 | D28: =+C28/2 -> 40500 | E28: =+D28 -> 40500 | F28: 81000
A29: 46135 | B29: 4 | C29: 69000 | D29: =+C29/2 -> 34500 | E29: =+D29 -> 34500 | F29: 33000
A30: 46136 | B30: 8 | C30: 96000 | D30: =+C30/2 -> 48000 | E30: =+D30 -> 48000 | F30: 81000
A31: 46137 | B31: 3 | C31: 48000 | D31: =+C31/2 -> 24000 | E31: =+D31 -> 24000 | F31: 30000
A32: Total | B32: =SUM(B27:B31) -> 24 | C32: =SUM(C27:C31) -> 327000 | D32: =SUM(D27:D31) -> 163500 | E32: =SUM(E27:E31) -> 163500 | F32: =SUM(F27:F31) -> 258000
A34: SEMANA 5
A35: 46140 | B35: 3 | C35: 51000 | D35: =+C35/2 -> 25500 | E35: =+D35 -> 25500 | F35: 33000
A36: 46141 | B36: 4 | C36: 33000 | D36: =+C36/2 -> 16500 | E36: =+D36 -> 16500 | F36: 33000
A37: 46142 | B37: 8 | C37: 128000 | D37: =+C37/2 -> 64000 | E37: =+D37 -> 64000 | F37: 103000
D38: =+C38/2 -> 0 | E38: =+D38 -> 0
D39: =+C39/2 -> 0 | E39: =+D39 -> 0
A40: Total | B40: =SUM(B35:B39) -> 15 | C40: =SUM(C35:C39) -> 212000 | D40: =SUM(D35:D39) -> 106000 | E40: =SUM(E35:E39) -> 106000 | F40: =SUM(F35:F39) -> 169000

Sheet FABRICIO
A1: FECHA | B1: Cant. | C1: Total Facturado | D1: VALHALLA | E1: FABRICIO | F1: TRANSF.
A2: SEMANA 1 | H2: Total | I2: =C8+C16+C24+C32+C40 -> 2511000
D3: =+C3/2 -> 0 | E3: =+D3 -> 0 | H3: Total VALHALLA | I3: =D8+D16+D24+D32+D40 -> 1210500
A4: 46113 | B4: 12 | C4: 180000 | D4: =+C4/2 -> 90000 | E4: =+D4 -> 90000 | F4: 95000 | H4: Total Fabricio | I4: =E8+E16+E24+E32+E40 -> 1300500
A5: 46114 | B5: 6 | C5: 105000 | D5: 36300 | E5: 68700 | F5: 105000
A6: 46115 | B6: 9 | C6: 132000 | D6: 37200 | E6: 94800 | F6: 66000 | H6: Total CORTES | I6: =+B8+B16+B24+B32+B40 -> 147
A7: 46116 | B7: 6 | C7: 112000 | D7: =+C7/2 -> 56000 | E7: =+D7 -> 56000 | F7: 112000
A8: Total | B8: =SUM(B3:B7) -> 33 | C8: =SUM(C2:C7) -> 529000 | D8: =SUM(D2:D7) -> 219500 | E8: =SUM(E2:E7) -> 309500 | F8: =SUM(F3:F7) -> 378000
A10: SEMANA 2
A11: 46119 | B11: 4 | C11: 73000 | D11: =+C11/2 -> 36500 | E11: =+D11 -> 36500 | F11: 55000
A12: 46120 | B12: 6 | C12: 108000 | D12: =+C12/2 -> 54000 | E12: =+D12 -> 54000 | F12: 75000
A13: 46121 | B13: 5 | C13: 91000 | D13: =+C13/2 -> 45500 | E13: =+D13 -> 45500 | F13: 58000
A14: 46122 | B14: 10 | C14: 165000 | D14: =+C14/2 -> 82500 | E14: =+D14 -> 82500 | F14: 105000
A15: 46123 | B15: 4 | C15: 70000 | D15: =+C15/2 -> 35000 | E15: =+D15 -> 35000 | F15: 30000
A16: Total | B16: =SUM(B11:B15) -> 29 | C16: =SUM(C11:C15) -> 507000 | D16: =SUM(D11:D15) -> 253500 | E16: =SUM(E11:E15) -> 253500 | F16: =SUM(F11:F15) -> 323000
A18: SEMANA 3
A19: 46126 | B19: 5 | C19: 90000 | D19: =+C19/2 -> 45000 | E19: =+D19 -> 45000 | F19: 90000
A20: 46127 | B20: 2 | C20: 33000 | D20: =+C20/2 -> 16500 | E20: =+D20 -> 16500 | F20: 15000
A21: 46128 | B21: 8 | C21: 141000 | D21: =+C21/2 -> 70500 | E21: =+D21 -> 70500 | F21: 87000
A22: 46129 | B22: 11 | C22: 179000 | D22: =+C22/2 -> 89500 | E22: =+D22 -> 89500 | F22: 129000
A23: 46130 | B23: 6 | C23: 106000 | D23: =+C23/2 -> 53000 | E23: =+D23 -> 53000 | F23: 67000
A24: Total | B24: =SUM(B19:B23) -> 32 | C24: =SUM(C19:C23) -> 549000 | D24: =SUM(D19:D23) -> 274500 | E24: =SUM(E19:E23) -> 274500 | F24: =SUM(F19:F23) -> 388000
A26: SEMANA 4
A27: 46133 | B27: 3 | C27: 48000 | D27: =+C27/2 -> 24000 | E27: =+D27 -> 24000 | F27: 48000
A28: 46134 | B28: 4 | C28: 66000 | D28: =+C28/2 -> 33000 | E28: =+D28 -> 33000 | F28: 48000
A29: 46135 | B29: 8 | C29: 140000 | D29: =+C29/2 -> 70000 | E29: =+D29 -> 70000 | F29: 54000
A30: 46136 | B30: 7 | C30: 127000 | D30: =+C30/2 -> 63500 | E30: =+D30 -> 63500 | F30: 109000
A31: 46137 | B31: 8 | C31: 127000 | D31: =+C31/2 -> 63500 | E31: =+D31 -> 63500 | F31: 109000
A32: Total | B32: =SUM(B27:B31) -> 30 | C32: =SUM(C27:C31) -> 508000 | D32: =SUM(D27:D31) -> 254000 | E32: =SUM(E27:E31) -> 254000 | F32: =SUM(F27:F31) -> 368000
A34: SEMANA 5
A35: 46140 | B35: 5 | C35: 88000 | D35: =+C35/2 -> 44000 | E35: =+D35 -> 44000 | F35: 73000
A36: 46141 | B36: 7 | C36: 128000 | D36: =+C36/2 -> 64000 | E36: =+D36 -> 64000 | F36: 91000
A37: 46142 | B37: 11 | C37: 202000 | D37: =+C37/2 -> 101000 | E37: =+D37 -> 101000 | F37: 161000
D38: =+C38/2 -> 0 | E38: =+D38 -> 0
D39: =+C39/2 -> 0 | E39: =+D39 -> 0
A40: Total | B40: =SUM(B35:B39) -> 23 | C40: =SUM(C35:C39) -> 418000 | D40: =SUM(D35:D39) -> 209000 | E40: =SUM(E35:E39) -> 209000 | F40: =SUM(F35:F39) -> 325000

Sheet GERONIMO 
A1: FECHA | B1: Cant. | C1: Total Facturado | D1: VALHALLA | E1: GERONIMO
A2: SEMANA 1 | G2: Total | H2: =C8+C16+C24+C32+C40 -> 1595000 | K2: DIAS | L2: Cant. | M2: Total Facturado | N2: Básico | O2: Presentismo | Q2: Objetivo | S2: Total Geronimo
D3: =+C3-E3 -> 0 | E3: =+C3*0.5 -> 0 | G3: Total VALHALLA | H3: =D8+D16+D24+D32+D40 -> 822750 | K3: Semana 1 | L3: =+B8 -> 17 | M3: =+C8 -> 322000 | N3: =+M3*0.4 -> 128800 | O3: Si | P3: =+IF(O3="si",+M3*0.05,0) -> 16100 | Q3: Si | R3: =+IF(Q3="si",+M3*0.05,0) -> 16100 | S3: =+N3+P3+R3 -> 161000
A4: 46113 | B4: 5 | C4: 98000 | D4: =+C4-E4 -> 49000 | E4: =+C4*0.5 -> 49000 | G4: Total GERONIMO | H4: =E8+E16+E24+E32+E40 -> 772250 | K4: Semana 2 | L4: =+B16 -> 24 | M4: =+C16 -> 417000 | N4: =+M4*0.4 -> 166800 | O4: Si | P4: =+IF(O4="si",+M4*0.05,0) -> 20850 | Q4: Si | R4: =+IF(Q4="si",+M4*0.05,0) -> 20850 | S4: =+N4+P4+R4 -> 208500
A5: 46114 | B5: 4 | C5: 69000 | D5: =+C5-E5 -> 34500 | E5: =+C5*0.5 -> 34500 | K5: Semana 3 | L5: =+B24 -> 20 | M5: =+C24 -> 351000 | N5: =+M5*0.4 -> 140400 | O5: Si | P5: =+IF(O5="si",+M5*0.05,0) -> 17550 | Q5: Si | R5: =+IF(Q5="si",+M5*0.05,0) -> 17550 | S5: =+N5+P5+R5 -> 175500
A6: 46115 | B6: 2 | C6: 36000 | D6: =+C6-E6 -> 18000 | E6: =+C6*0.5 -> 18000 | G6: Total CORTES | H6: =+B8+B16+B24+B32+B40 -> 90 | K6: Semana 4 | L6: =+B32 -> 19 | M6: =+C32 -> 328000 | N6: =+M6*0.4 -> 131200 | O6: Si | P6: =+IF(O6="si",+M6*0.05,0) -> 16400 | Q6: No | R6: =+IF(Q6="si",+M6*0.05,0) -> 0 | S6: =+N6+P6+R6 -> 147600
A7: 46116 | B7: 6 | C7: 119000 | D7: =+C7-E7 -> 59500 | E7: =+C7*0.5 -> 59500 | K7: Semana 5 | L7: =+B40 -> 10 | M7: =+C40 -> 177000 | N7: =+M7*0.4 -> 70800 | O7: Si | P7: =+IF(O7="si",+M7*0.05,0) -> 8850 | Q7: No | R7: =+IF(Q7="si",+M7*0.05,0) -> 0 | S7: =+N7+P7+R7 -> 79650
A8: Total | B8: =SUM(B3:B7) -> 17 | C8: =SUM(C2:C7) -> 322000 | D8: =SUM(D2:D7) -> 161000 | E8: =SUM(E2:E7) -> 161000 | K8: TOTAL | L8: =SUM(L3:L7) -> 90 | M8: =SUM(M3:M7) -> 1595000 | N8: =SUM(N3:N7) -> 638000 | O8: =SUM(O3:O7) -> 0 | P8: =SUM(P3:P7) -> 79750 | Q8: =SUM(Q3:Q7) -> 0 | R8: =SUM(R3:R7) -> 54500 | S8: =SUM(S3:S7) -> 772250
A10: SEMANA 2
A11: 46119 | B11: 4 | C11: 69000 | D11: =+C11-E11 -> 34500 | E11: =+C11*0.5 -> 34500
A12: 46120 | B12: 6 | C12: 105000 | D12: =+C12-E12 -> 52500 | E12: =+C12*0.5 -> 52500
A13: 46121 | B13: 4 | C13: 72000 | D13: =+C13-E13 -> 36000 | E13: =+C13*0.5 -> 36000
A14: 46122 | B14: 6 | C14: 102000 | D14: =+C14-E14 -> 51000 | E14: =+C14*0.5 -> 51000
A15: 46123 | B15: 4 | C15: 69000 | D15: =+C15-E15 -> 34500 | E15: =+C15*0.5 -> 34500
A16: Total | B16: =SUM(B11:B15) -> 24 | C16: =SUM(C11:C15) -> 417000 | D16: =SUM(D11:D15) -> 208500 | E16: =SUM(E11:E15) -> 208500
A18: SEMANA 3
A19: 46126 | B19: 2 | C19: 33000 | D19: =+C19-E19 -> 16500 | E19: =+C19*0.5 -> 16500
A20: 46127 | B20: 5 | C20: 69000 | D20: =+C20-E20 -> 34500 | E20: =+C20*0.5 -> 34500
A21: 46128 | B21: 3 | C21: 61000 | D21: =+C21-E21 -> 30500 | E21: =+C21*0.5 -> 30500
A22: 46129 | B22: 4 | C22: 72000 | D22: =+C22-E22 -> 36000 | E22: =+C22*0.5 -> 36000
A23: 46130 | B23: 6 | C23: 116000 | D23: =+C23-E23 -> 58000 | E23: =+C23*0.5 -> 58000
A24: Total | B24: =SUM(B19:B23) -> 20 | C24: =SUM(C19:C23) -> 351000 | D24: =SUM(D19:D23) -> 175500 | E24: =SUM(E19:E23) -> 175500
A26: SEMANA 4
A27: 46133 | B27: 4 | C27: 60000 | D27: =+C27-E27 -> 33000 | E27: =+C27*0.45 -> 27000
A28: 46134 | B28: 2 | C28: 33000 | D28: =+C28-E28 -> 18150 | E28: =+C28*0.45 -> 14850
A29: 46135 | B29: 3 | C29: 54000 | D29: =+C29-E29 -> 29700 | E29: =+C29*0.45 -> 24300
A30: 46136 | B30: 6 | C30: 108000 | D30: =+C30-E30 -> 59400 | E30: =+C30*0.45 -> 48600
A31: 46137 | B31: 4 | C31: 73000 | D31: =+C31-E31 -> 40150 | E31: =+C31*0.45 -> 32850
A32: Total | B32: =SUM(B27:B31) -> 19 | C32: =SUM(C27:C31) -> 328000 | D32: =SUM(D27:D31) -> 180400 | E32: =SUM(E27:E31) -> 147600
A34: SEMANA 5
A35: 46140 | B35: 3 | C35: 54000 | D35: =+C35-E35 -> 29700 | E35: =+C35*0.45 -> 24300
A36: 46141 | B36: 2 | C36: 36000 | D36: =+C36-E36 -> 19800 | E36: =+C36*0.45 -> 16200
A37: 46142 | B37: 5 | C37: 87000 | D37: =+C37-E37 -> 47850 | E37: =+C37*0.45 -> 39150
D38: =C38*0.3 -> 0 | E38: =C38*0.7 -> 0
D39: =C39*0.3 -> 0 | E39: =C39*0.7 -> 0
A40: Total | B40: =SUM(B35:B39) -> 10 | C40: =SUM(C35:C39) -> 177000 | D40: =SUM(D35:D39) -> 97350 | E40: =SUM(E35:E39) -> 79650

Sheet BRUNO
A1: FECHA | B1: Cant. | C1: Total Facturado | D1: VALHALLA | E1: BRUNO | F1: TRANSF.
A2: SEMANA 1 | H2: Total | I2: =C8+C16+C24+C32+C40 -> 1685000 | K2: DIAS | L2: Cant. | M2: Total Facturado | N2: Básico | O2: Presentismo | Q2: Objetivo | S2: Total Bruno
D3: =+C3-E3 -> 0 | E3: =+C3*0.45 -> 0 | H3: Total VALHALLA | I3: =D8+D16+D24+D32+D40 -> 866800 | K3: Semana 1 | L3: =+B8 -> 15 | M3: =+C8 -> 257000 | N3: =+M3*0.4 -> 102800 | O3: Si | P3: =+IF(O3="si",+M3*0.05,0) -> 12850 | Q3: Si | R3: =+IF(Q3="si",+M3*0.05,0) -> 12850 | S3: =+N3+P3+R3 -> 128500
A4: 46113 | B4: 4 | C4: 72000 | D4: =+C4-E4 -> 36000 | E4: =+C4*0.5 -> 36000 | H4: Total BRUNO | I4: =E8+E16+E24+E32+E40 -> 818200 | K4: Semana 2 | L4: =+B16 -> 28 | M4: =+C16 -> 474000 | N4: =+M4*0.4 -> 189600 | O4: Si | P4: =+IF(O4="si",+M4*0.05,0) -> 23700 | Q4: Si | R4: =+IF(Q4="si",+M4*0.05,0) -> 23700 | S4: =+N4+P4+R4 -> 237000
A5: 46114 | B5: 5 | C5: 87000 | D5: =+C5-E5 -> 43500 | E5: =+C5*0.5 -> 43500 | K5: Semana 3 | L5: =+B24 -> 28 | M5: =+C24 -> 468000 | N5: =+M5*0.4 -> 187200 | O5: Si | P5: =+IF(O5="si",+M5*0.05,0) -> 23400 | Q5: Si | R5: =+IF(Q5="si",+M5*0.05,0) -> 23400 | S5: =+N5+P5+R5 -> 234000
A6: 46115 | D6: =+C6-E6 -> 0 | E6: =+C6*0.45 -> 0 | H6: Total CORTES | I6: =+B8+B16+B24+B32+B40 -> 98 | K6: Semana 4 | L6: =+B32 -> 18 | M6: =+C32 -> 323000 | N6: =+M6*0.4 -> 129200 | O6: Si | P6: =+IF(O6="si",+M6*0.05,0) -> 16150 | Q6: No | R6: =+IF(Q6="si",+M6*0.05,0) -> 0 | S6: =+N6+P6+R6 -> 145350
A7: 46116 | B7: 6 | C7: 98000 | D7: =+C7-E7 -> 49000 | E7: =+C7*0.5 -> 49000 | K7: Semana 5 | L7: =+B40 -> 9 | M7: =+C40 -> 163000 | N7: =+M7*0.4 -> 65200 | O7: Si | P7: =+IF(O7="si",+M7*0.05,0) -> 8150 | Q7: No | R7: =+IF(Q7="si",+M7*0.05,0) -> 0 | S7: =+N7+P7+R7 -> 73350
A8: Total | B8: =SUM(B3:B7) -> 15 | C8: =SUM(C2:C7) -> 257000 | D8: =+C8-E8 -> 128500 | E8: =+S3 -> 128500 | F8: =SUM(F3:F7) -> 0 | K8: TOTAL | L8: =SUM(L3:L7) -> 98 | M8: =SUM(M3:M7) -> 1685000 | N8: =SUM(N3:N7) -> 674000 | O8: =SUM(O3:O7) -> 0 | P8: =SUM(P3:P7) -> 84250 | Q8: =SUM(Q3:Q7) -> 0 | R8: =SUM(R3:R7) -> 59950 | S8: =SUM(S3:S7) -> 818200
A10: SEMANA 2
A11: 46119 | B11: 4 | C11: 66000 | D11: =+C11-E11 -> 33000 | E11: =+C11*0.5 -> 33000
A12: 46120 | B12: 3 | C12: 51000 | D12: =+C12-E12 -> 25500 | E12: =+C12*0.5 -> 25500
A13: 46121 | B13: 6 | C13: 99000 | D13: =+C13-E13 -> 49500 | E13: =+C13*0.5 -> 49500
A14: 46122 | B14: 8 | C14: 132000 | D14: =+C14-E14 -> 66000 | E14: =+C14*0.5 -> 66000
A15: 46123 | B15: 7 | C15: 126000 | D15: =+C15-E15 -> 63000 | E15: =+C15*0.5 -> 63000
A16: Total | B16: =SUM(B11:B15) -> 28 | C16: =SUM(C11:C15) -> 474000 | D16: =SUM(D11:D15) -> 237000 | E16: =SUM(E11:E15) -> 237000 | F16: =SUM(F11:F15) -> 0
A18: SEMANA 3
A19: 46126 | B19: 4 | C19: 76000 | D19: =+C19-E19 -> 38000 | E19: =+C19*0.5 -> 38000
A20: 46127 | B20: 5 | C20: 85000 | D20: =+C20-E20 -> 42500 | E20: =+C20*0.5 -> 42500
A21: 46128 | B21: 5 | C21: 84000 | D21: =+C21-E21 -> 42000 | E21: =+C21*0.5 -> 42000
A22: 46129 | B22: 7 | C22: 120000 | D22: =+C22-E22 -> 60000 | E22: =+C22*0.5 -> 60000
A23: 46130 | B23: 7 | C23: 103000 | D23: =+C23-E23 -> 51500 | E23: =+C23*0.5 -> 51500
A24: Total | B24: =SUM(B19:B23) -> 28 | C24: =SUM(C19:C23) -> 468000 | D24: =SUM(D19:D23) -> 234000 | E24: =SUM(E19:E23) -> 234000 | F24: =SUM(F19:F23) -> 0
A26: SEMANA 4
A27: 46133 | B27: 2 | C27: 36000 | D27: =+C27-E27 -> 19800 | E27: =+C27*0.45 -> 16200
A28: 46134 | B28: 1 | C28: 15000 | D28: =+C28-E28 -> 8250 | E28: =+C28*0.45 -> 6750
A29: 46135 | B29: 6 | C29: 109000 | D29: =+C29-E29 -> 59950 | E29: =+C29*0.45 -> 49050
A30: 46136 | B30: 5 | C30: 94000 | D30: =+C30-E30 -> 51700 | E30: =+C30*0.45 -> 42300
A31: 46137 | B31: 4 | C31: 69000 | D31: =+C31-E31 -> 37950 | E31: =+C31*0.45 -> 31050
A32: Total | B32: =SUM(B27:B31) -> 18 | C32: =SUM(C27:C31) -> 323000 | D32: =SUM(D27:D31) -> 177650 | E32: =SUM(E27:E31) -> 145350 | F32: =SUM(F27:F31) -> 0
A34: SEMANA 5
A35: 46140 | B35: 2 | C35: 43000 | D35: =+C35-E35 -> 23650 | E35: =+C35*0.45 -> 19350
A36: 46141 | B36: 3 | C36: 51000 | D36: =+C36-E36 -> 28050 | E36: =+C36*0.45 -> 22950
A37: 46142 | B37: 4 | C37: 69000 | D37: =+C37-E37 -> 37950 | E37: =+C37*0.45 -> 31050
D38: =+C38-E38 -> 0 | E38: =+C38*0.45 -> 0
D39: =+C39-E39 -> 0 | E39: =+C39*0.45 -> 0
A40: Total | B40: =SUM(B35:B39) -> 9 | C40: =SUM(C35:C39) -> 163000 | D40: =SUM(D35:D39) -> 89650 | E40: =SUM(E35:E39) -> 73350 | F40: =SUM(F35:F39) -> 0

Sheet GASTOS
A1: PLANILLA DE GASTOS MENSUALES
A2: Concepto | B2: Fecha | C2: TOTAL | E2: TOTAL
E3: =+SUM(C4:C52) -> 4097493
A4: Alquiler SESE | B4: 46118 | C4: 380000
A5: Seguro Cuota 1 | B5: 46118 | C5: 50836
A6: Nube JESUS | B6: 46118 | C6: 8300
A7: Sistema JESUS | B7: 46118 | C7: 53122
A8: Stella Gaspar | B8: 46118 | C8: 80000
A9: Dispenser Jesus | B9: 46118 | C9: 25000
A10: Contadora Jesus | B10: 46118 | C10: 60000
A11: CM Guille Jesus | B11: 46118 | C11: 33300
A12: Barberium Gaspar | B12: 46118 | C12: 173100
A13: Ministerio 19 SESE | B13: 46118 | C13: 32150
A14: Internet Claro SESE | B14: 46118 | C14: 37300
A15: Aro De Luz Gero 2/9 JESUS | B15: 46118 | C15: 15238
... A46: Regalo corte sese | B46: 46146 | C46: 10000
D52: =+SUM(C4:C52) -> 4097493

Sheet INGRESOS
A1: TOTAL GENERADO | B1: =+FRANCO!H2+'LAUREANO '!I2+FABRICIO!I2+BEIZEN!I2+BRUNO!I2+'GERONIMO '!H2 -> 12559000
A3: VALHALLA | B3: =+FRANCO!H3+'LAUREANO '!I3+FABRICIO!I3+BEIZEN!I3+BRUNO!I3+'GERONIMO '!H3 -> 6290050 | F3: DIVISION ENTRE SOCIOS
A4: GERONIMO | B4: =+'GERONIMO '!H4 -> 772250 | F4: NOMBRE | G4: PORCENTAJE | H4: MONTO
A5: BRUNO | B5: =+BRUNO!I4 -> 818200 | F5: JESUS | G5: 0.4 | H5: =+'SALDOS REALES'!$B$5*G5 -> 2746754.8
A6: LAUREANO | B6: =+'LAUREANO '!I4 -> 1352000 | F6: GASPAR | G6: 0.3 | H6: =+'SALDOS REALES'!$B$5*G6 -> 2060066.1
A7: BEIZEN | B7: =+BEIZEN!I4 -> 763000 | F7: EZEQUIEL | G7: 0.3 | H7: =+'SALDOS REALES'!$B$5*G7 -> 2060066.1
A8: FRANCO | B8: =+FRANCO!H4 -> 1263000 | H8: TOTAL | I8: =+SUM(H5:H7) -> 6866887
A9: FABRICIO | B9: =+FABRICIO!I4 -> 1300500
A11: TOTAL | B11: =SUM(B3:B9) -> 12559000

Sheet SALDOS REALES
B1: Efectivo
A2: SALDO ANTERIOR | B2: 4674330 | D2: Deudas
A3: INGRESOS | B3: =+INGRESOS!B3 -> 6290050 | D3: * Lauro | E3: 815000
A4: GASTOS | B4: =-GASTOS!E3 -> -4097493
A5: SALDO ACTUAL | B5: =SUM(B2:B4) -> 6866887

Sheet Datos 
B2: Nombre y Apellido | C2: Dni | D2: Fecha de Nacimiento
B3: Laureano Joel Medina | C3: 41055939 | D3: 35910
B4: Franco Inspide | D4: 36415
B5: Fabricio Tirabassi | C5: 40780435 | D5: 35768
B6: Agustin Bazan | C6: 41406369 | D6: 36174
B7: Juani Troncoso
